MANIFEST.in
README.md
setup.py
intellisense/__init__.py
intellisense/client.py
intellisense/errors.py
intellisense/options.py
intellisense/stats.py
intellisense/utils.py
intellisense/version.py
intellisense_python.egg-info/PKG-INFO
intellisense_python.egg-info/SOURCES.txt
intellisense_python.egg-info/dependency_links.txt
intellisense_python.egg-info/requires.txt
intellisense_python.egg-info/top_level.txt