Metadata-Version: 1.1
Name: intellisense-python
Version: 1.0.0
Summary: Intellisense API for Python.  Provides implementation for Caliper Sensor API and more
Home-page: https://github.com/pnayak/intellisense-python.git
Author: Intellify Learning
Author-email: founders@intellifylearning.com
License: Intellify Learning
Platform: UNKNOWN
Classifier: Development Status :: 5 - Production/Stable
Classifier: Topic :: Sensor
Classifier: License :: Proprietary License :: Intellify License
